[
    {
        "id": "event_campfire",
        "title": "Event: Campfire",
        "subtitle": "Lagerfeuer-Geschichten",
        "sortOrder": 112,
        "endsAt": "19.06.2026 23:59",
        "minAscendedLevel": 10,
        "mapTexture": "realm_campfire",
        "nodeImage": "chest_campfire",
        "cutscene": {
            "id": "event_shukuwa_intro",
            "title": "Begegnung am Lagerfeuer",
            "video": "intro_campfire",
            "text":
                "Ein seltsamer, aber warmer Ort zieht die Gefährten tief in den Wald, wo unbekannte Kreaturen warten."
        },
        "points": [
            {
                "id": "event_shukuwa_field",
                "title": "Das Shukwa-Lager",
                "text":
                    "Eine friedliche Oase inmitten der Wildnis, bewacht von mystischen Wesen.",
                "mapImage": "realm_campfire",
                "mapTexture": "realm_campfire",
                "node": {
                    "x": 0.5,
                    "y": 0.5
                },
                "battleGenerator": {
                    "count": 50,
                    "enemyIDs": [
                        "shinuca",
                        "shinuca_awakening"
                    ],
                    "groupSize": 3,
                    "namePrefix": "Shinuca Campfire",
                    "description": "Kampf mit Shinuca-Gegnern.",
                    "startDifficulty": 8,
                    "difficultyEvery": 5,
                    "difficultyStep": 1,
                    "xpReward": 360,
                    "rewards": [
                        {
                            "currency": "coins",
                            "amount": 180
                        },
                        {
                            "currency": "crystals",
                            "amount": 8
                        }
                    ],
                    "groundTexture": "realm_campfire",
                    "skyboxTexture": "realm_campfire"
                },
                "battles": []
            }
        ]
    }
]
